RealtimeSTT/__init__.py
RealtimeSTT/audio_input.py
RealtimeSTT/audio_recorder.py
RealtimeSTT/audio_recorder_client.py
RealtimeSTT/safepipe.py
RealtimeSTT/warmup_audio.wav
RealtimeSTT_server/__init__.py
RealtimeSTT_server/install_packages.py
RealtimeSTT_server/stt_cli_client.py
RealtimeSTT_server/stt_server.py
realtimestt-0.3.104.dist-info/licenses/LICENSE
realtimestt-0.3.104.dist-info/METADATA
realtimestt-0.3.104.dist-info/WHEEL
realtimestt-0.3.104.dist-info/entry_points.txt
realtimestt-0.3.104.dist-info/top_level.txt
realtimestt-0.3.104.dist-info/RECORD
